aitoolkit/__init__.py
aitoolkit/py.typed
aitoolkit/utils/__init__.py
aitoolkit/utils/file/__init__.py
aitoolkit/utils/file/split_jsonl.py
cqh_ai_toolkit-0.1.3.dist-info/METADATA
cqh_ai_toolkit-0.1.3.dist-info/WHEEL
cqh_ai_toolkit-0.1.3.dist-info/licenses/LICENSE
cqh_ai_toolkit-0.1.3.dist-info/RECORD
