Metadata-Version: 2.3
Name: cqh-ai-toolkit
Version: 0.1.3
Summary: A toolkit for AI
Author-email: Qianhe Chen <qianhechen01@gmail.com>
License: MIT
Keywords: ai,toolkit
Classifier: Development Status :: 3 - Alpha
Classifier: Intended Audience :: Developers
Classifier: License :: OSI Approved :: MIT License
Classifier: Programming Language :: Python :: 3
Classifier: Programming Language :: Python :: 3.10
Requires-Python: >=3.10
Requires-Dist: ruff>=0.7.4
